[
  {
    "campeonato": "Bundesliga",
    "hora": "16:30",
    "time_casa": {
      "nome": "Augsburg",
      "img": "https://static.futbolenlatv.com/img/32/20121218101607_augsburgo.webp"
    },
    "time_visitante": {
      "nome": "Union Berlin",
      "img": "https://static.futbolenlatv.com/img/32/20130126035044_union_berlin.webp"
    },
    "canais": [
      "OneFootball PPV",
      "OneFootball"
    ]
  },
  {
    "campeonato": "Campeonato Alagoano",
    "hora": "20:00",
    "time_casa": {
      "nome": "CRB",
      "img": "https://static.futbolenlatv.com/img/32/20130510121115_crb.webp"
    },
    "time_visitante": {
      "nome": "Murici",
      "img": "https://static.futbolenlatv.com/img/32/20180209112057-murici.webp"
    },
    "canais": [
      "SportyNet+ Plus",
      "NN Play YouTube"
    ]
  },
  {
    "campeonato": "Campeonato Baiano",
    "hora": "19:15",
    "time_casa": {
      "nome": "Jequié",
      "img": "https://static.futbolenlatv.com/img/32/20180118102117-jequie.webp"
    },
    "time_visitante": {
      "nome": "Porto Sport Club BA",
      "img": "https://static.futbolenlatv.com/img/32/20250112200735-porto-sport-club-ba.webp"
    },
    "canais": [
      "TVE Bahía"
    ]
  },
  {
    "campeonato": "Campeonato Capixaba",
    "hora": "19:00",
    "time_casa": {
      "nome": "Real Noroeste",
      "img": "https://static.futbolenlatv.com/img/32/20200308215437-real-noroeste-capixaba.webp"
    },
    "time_visitante": {
      "nome": "Forte FC",
      "img": "https://static.futbolenlatv.com/img/32/20220102152119-forte-futebol-clube.webp"
    },
    "canais": [
      "TVE Espírito Santo"
    ]
  },
  {
    "campeonato": "Campeonato Carioca",
    "hora": "17:00",
    "time_casa": {
      "nome": "Sampaio Correa",
      "img": "https://static.futbolenlatv.com/img/32/20150424124026-sampaio-correa.webp"
    },
    "time_visitante": {
      "nome": "Nova Iguaçu",
      "img": "https://static.futbolenlatv.com/img/32/20180117113635-nova-iguacu.webp"
    },
    "canais": [
      "Premiere"
    ]
  },
  {
    "campeonato": "Campeonato Carioca",
    "hora": "19:00",
    "time_casa": {
      "nome": "Portuguesa RJ",
      "img": "https://static.futbolenlatv.com/img/32/20180117121509-portuguesa-rj.webp"
    },
    "time_visitante": {
      "nome": "Botafogo RJ",
      "img": "https://static.futbolenlatv.com/img/32/20121222101953_botafogo.webp"
    },
    "canais": [
      "Premiere"
    ]
  },
  {
    "campeonato": "Campeonato Carioca",
    "hora": "21:30",
    "time_casa": {
      "nome": "Vasco",
      "img": "https://static.futbolenlatv.com/img/32/20121222111424_vasco-da-gama.webp"
    },
    "time_visitante": {
      "nome": "Maricá FC",
      "img": "https://static.futbolenlatv.com/img/32/20220123114831-marica-cf.webp"
    },
    "canais": [
      "Ge TV",
      "SporTV",
      "Premiere"
    ]
  },
  {
    "campeonato": "Campeonato Catarinense",
    "hora": "20:00",
    "time_casa": {
      "nome": "Joinville",
      "img": "https://static.futbolenlatv.com/img/32/20130501080349_joinville.webp"
    },
    "time_visitante": {
      "nome": "Criciuma",
      "img": "https://static.futbolenlatv.com/img/32/20121222102413_criciuma.webp"
    },
    "canais": [
      "SportyNet",
      "SportyNet YouTube"
    ]
  },
  {
    "campeonato": "Campeonato Catarinense",
    "hora": "20:30",
    "time_casa": {
      "nome": "Marcílio Dias",
      "img": "https://static.futbolenlatv.com/img/32/20200308215450-cluba-nautico-marcilio-dias.webp"
    },
    "time_visitante": {
      "nome": "Santa Catarina",
      "img": "https://static.futbolenlatv.com/img/32/20241203182558-santa-catarina-clube.webp"
    },
    "canais": [
      "SportyNet+ Plus"
    ]
  },
  {
    "campeonato": "Campeonato Cearense",
    "hora": "20:30",
    "time_casa": {
      "nome": "Fortaleza",
      "img": "https://static.futbolenlatv.com/img/32/20160516115803-fortaleza-sc.webp"
    },
    "time_visitante": {
      "nome": "Quixada FC",
      "img": "https://static.futbolenlatv.com/img/32/20251216182546-quixada-fc-ce-academy.webp"
    },
    "canais": [
      "Canal GOAT",
      "GE.Globo",
      "Ge TV"
    ]
  },
  {
    "campeonato": "Campeonato Goiano",
    "hora": "18:30",
    "time_casa": {
      "nome": "Inhumas EC",
      "img": "https://static.futbolenlatv.com/img/32/20221211002543-inhumas-esporte-clube.webp"
    },
    "time_visitante": {
      "nome": "ABECAT Ouvidorense",
      "img": "https://static.futbolenlatv.com/img/32/20250119214030-abecat-ouvidorense.webp"
    },
    "canais": [
      "TV Brasil Central"
    ]
  },
  {
    "campeonato": "Campeonato Goiano",
    "hora": "19:30",
    "time_casa": {
      "nome": "CRAC",
      "img": "https://static.futbolenlatv.com/img/32/20200308215356-clube-recreativo-atletico-catalano.webp"
    },
    "time_visitante": {
      "nome": "Goias",
      "img": "https://static.futbolenlatv.com/img/32/20190115105819-goias.webp"
    },
    "canais": [
      "Canal GOAT"
    ]
  },
  {
    "campeonato": "Campeonato Goiano",
    "hora": "20:40",
    "time_casa": {
      "nome": "Aparecidense",
      "img": "https://static.futbolenlatv.com/img/32/20180201105716-aparecidense.webp"
    },
    "time_visitante": {
      "nome": "Atletico GO",
      "img": "https://static.futbolenlatv.com/img/32/20200902145907-atletico-goianiense.webp"
    },
    "canais": [
      "TV Brasil Central"
    ]
  },
  {
    "campeonato": "Campeonato italiano",
    "hora": "14:30",
    "time_casa": {
      "nome": "Verona",
      "img": "https://static.futbolenlatv.com/img/32/20200907114144-hellas-verona.webp"
    },
    "time_visitante": {
      "nome": "Bologna",
      "img": "https://static.futbolenlatv.com/img/32/20121219035023_bologna.webp"
    },
    "canais": [
      "Disney+ Premium",
      "ESPN 2"
    ]
  },
  {
    "campeonato": "Campeonato italiano",
    "hora": "16:45",
    "time_casa": {
      "nome": "Como",
      "img": "https://static.futbolenlatv.com/img/32/20211013183924-calcio-como.webp"
    },
    "time_visitante": {
      "nome": "AC Milan",
      "img": "https://static.futbolenlatv.com/img/32/20121219034733_milan.webp"
    },
    "canais": [
      "Disney+ Premium",
      "CazéTV YouTube",
      "CazeTV"
    ]
  },
  {
    "campeonato": "Campeonato Paranaense",
    "hora": "19:00",
    "time_casa": {
      "nome": "Independiente São Joseense",
      "img": "https://static.futbolenlatv.com/img/32/20220201110716-independiente-fsj.webp"
    },
    "time_visitante": {
      "nome": "Cianorte",
      "img": "https://static.futbolenlatv.com/img/32/20180227120109-cianorte.webp"
    },
    "canais": [
      "Canal GOAT"
    ]
  },
  {
    "campeonato": "Campeonato Paulista",
    "hora": "19:00",
    "time_casa": {
      "nome": "Botafogo SP",
      "img": "https://static.futbolenlatv.com/img/32/20140129024719-botafogo.webp"
    },
    "time_visitante": {
      "nome": "Noroeste",
      "img": "https://static.futbolenlatv.com/img/32/20180203105600-noroeste.webp"
    },
    "canais": [
      "HBO Max"
    ]
  },
  {
    "campeonato": "Campeonato Paulista",
    "hora": "19:30",
    "time_casa": {
      "nome": "Bragantino",
      "img": "https://static.futbolenlatv.com/img/32/20200122125639-rb-bragantino.webp"
    },
    "time_visitante": {
      "nome": "Corinthians",
      "img": "https://static.futbolenlatv.com/img/32/20121222102336_corinthians.webp"
    },
    "canais": [
      "HBO Max",
      "CazeTV",
      "Paulistão YouTube",
      "RecordTV",
      "TNT",
      "CazéTV YouTube"
    ]
  },
  {
    "campeonato": "Campeonato Paulista",
    "hora": "21:45",
    "time_casa": {
      "nome": "Sao Paulo",
      "img": "https://static.futbolenlatv.com/img/32/20121222105631_sao-paulo.webp"
    },
    "time_visitante": {
      "nome": "Sao Bernardo",
      "img": "https://static.futbolenlatv.com/img/32/20200825070729-sao-bernardo.webp"
    },
    "canais": [
      "HBO Max",
      "TNT"
    ]
  },
  {
    "campeonato": "Copa del Rey",
    "hora": "17:00",
    "time_casa": {
      "nome": "Racing Santander",
      "img": "https://static.futbolenlatv.com/img/32/20121218095805_racing.webp"
    },
    "time_visitante": {
      "nome": "Barcelona",
      "img": "https://static.futbolenlatv.com/img/32/20121218093448_barcelona.webp"
    },
    "canais": [
      "Disney+ Premium",
      "ESPN"
    ]
  },
  {
    "campeonato": "Copa del Rey",
    "hora": "17:00",
    "time_casa": {
      "nome": "Burgos CF",
      "img": "https://static.futbolenlatv.com/img/32/20130523034010_burgos-cf.webp"
    },
    "time_visitante": {
      "nome": "Valencia",
      "img": "https://static.futbolenlatv.com/img/32/20151004120005-valencia.webp"
    },
    "canais": [
      "Disney+ Premium",
      "ESPN 4"
    ]
  },
  {
    "campeonato": "Copinha",
    "hora": "10:00",
    "time_casa": {
      "nome": "Fortaleza SC Academy",
      "img": "https://static.futbolenlatv.com/img/32/20160516115803-fortaleza-sc.webp"
    },
    "time_visitante": {
      "nome": "Itaquaquecetuba AC Academy",
      "img": "https://static.futbolenlatv.com/img/32/20251216102209-itaquaquecetuba-ac-academy.webp"
    },
    "canais": [
      "Xsports"
    ]
  },
  {
    "campeonato": "Copinha",
    "hora": "11:00",
    "time_casa": {
      "nome": "Internacional Academy",
      "img": "https://static.futbolenlatv.com/img/32/20121222103104_internacional.webp"
    },
    "time_visitante": {
      "nome": "Nacional SP Academy",
      "img": "https://static.futbolenlatv.com/img/32/20180122113737-nacional-sp.webp"
    },
    "canais": [
      "CazeTV"
    ]
  },
  {
    "campeonato": "Copinha",
    "hora": "14:30",
    "time_casa": {
      "nome": "RB Bragantino Academy",
      "img": "https://static.futbolenlatv.com/img/32/20200122125639-rb-bragantino.webp"
    },
    "time_visitante": {
      "nome": "Canaã EC Academy",
      "img": "https://static.futbolenlatv.com/img/32/20191224060348-canaa-ec.webp"
    },
    "canais": [
      "Xsports"
    ]
  },
  {
    "campeonato": "Copinha",
    "hora": "15:00",
    "time_casa": {
      "nome": "Palmeiras Academy",
      "img": "https://static.futbolenlatv.com/img/32/20130207042018_palmeiras.webp"
    },
    "time_visitante": {
      "nome": "AA Flamengo Academy",
      "img": "https://static.futbolenlatv.com/img/32/20191224060332-aa-flamengo.webp"
    },
    "canais": [
      "CazeTV"
    ]
  },
  {
    "campeonato": "Copinha",
    "hora": "15:00",
    "time_casa": {
      "nome": "Santo André Academy",
      "img": "https://static.futbolenlatv.com/img/32/20180118101544-santo-andre.webp"
    },
    "time_visitante": {
      "nome": "Ibrachina FC Academy",
      "img": "https://static.futbolenlatv.com/img/32/20210803231349-ibrachina-fc.webp"
    },
    "canais": [
      "Ulisses TV YouTube",
      "Ulisses TV"
    ]
  },
  {
    "campeonato": "Copinha",
    "hora": "17:00",
    "time_casa": {
      "nome": "Fluminense Academy",
      "img": "https://static.futbolenlatv.com/img/32/20180122105234-Fluminense.webp"
    },
    "time_visitante": {
      "nome": "Ituano Academy",
      "img": "https://static.futbolenlatv.com/img/32/20130207041958_ituano.webp"
    },
    "canais": [
      "CazeTV"
    ]
  },
  {
    "campeonato": "Copinha",
    "hora": "19:00",
    "time_casa": {
      "nome": "São Paulo Academy",
      "img": "https://static.futbolenlatv.com/img/32/20121222105631_sao-paulo.webp"
    },
    "time_visitante": {
      "nome": "Operário PR Academy",
      "img": "https://static.futbolenlatv.com/img/32/20180825104315-operario-pr.webp"
    },
    "canais": [
      "Xsports"
    ]
  },
  {
    "campeonato": "Copinha",
    "hora": "21:30",
    "time_casa": {
      "nome": "Juventude Academy",
      "img": "https://static.futbolenlatv.com/img/32/20160516120420-juventude.webp"
    },
    "time_visitante": {
      "nome": "Botafogo Academy",
      "img": "https://static.futbolenlatv.com/img/32/20121222101953_botafogo.webp"
    },
    "canais": [
      "Xsports"
    ]
  },
  {
    "campeonato": "Gaucho",
    "hora": "19:00",
    "time_casa": {
      "nome": "Ypiranga FC",
      "img": "https://static.futbolenlatv.com/img/32/20160701052940-ypiranga-fc.webp"
    },
    "time_visitante": {
      "nome": "Guarany de Bagé",
      "img": "https://static.futbolenlatv.com/img/32/20220124180252-guarany-bage.webp"
    },
    "canais": [
      "Ge TV"
    ]
  },
  {
    "campeonato": "Gaucho",
    "hora": "19:00",
    "time_casa": {
      "nome": "Monsoon FC",
      "img": "https://static.futbolenlatv.com/img/32/20250127132627-monsoon-fc.webp"
    },
    "time_visitante": {
      "nome": "Internacional",
      "img": "https://static.futbolenlatv.com/img/32/20121222103104_internacional.webp"
    },
    "canais": [
      "SporTV",
      "Premiere"
    ]
  },
  {
    "campeonato": "Liga MX",
    "hora": "00:10",
    "time_casa": {
      "nome": "Toluca",
      "img": "https://static.futbolenlatv.com/img/32/20170723095237-toluca.webp"
    },
    "time_visitante": {
      "nome": "Santos Laguna",
      "img": "https://static.futbolenlatv.com/img/32/20130210120959_santos-laguna.webp"
    },
    "canais": [
      "SportyNet"
    ]
  },
  {
    "campeonato": "Serie Río de la Plata",
    "hora": "18:15",
    "time_casa": {
      "nome": "Progreso",
      "img": "https://static.futbolenlatv.com/img/32/20200122120623-progreso.webp"
    },
    "time_visitante": {
      "nome": "Atlético Tucumán",
      "img": "https://static.futbolenlatv.com/img/32/20140815121718-atletico-tucuman.webp"
    },
    "canais": [
      "Disney+ Premium"
    ]
  },
  {
    "campeonato": "Serie Río de la Plata",
    "hora": "21:00",
    "time_casa": {
      "nome": "Olimpia Asuncion",
      "img": "https://static.futbolenlatv.com/img/32/20130412093209_olimpia.webp"
    },
    "time_visitante": {
      "nome": "Colo Colo",
      "img": "https://static.futbolenlatv.com/img/32/20130208052500_colo-colo.webp"
    },
    "canais": [
      "Disney+ Premium"
    ]
  }
]